NCMB/Client.py
NCMB/NCMBAcl.py
NCMB/NCMBGeoPoint.py
NCMB/NCMBObject.py
NCMB/NCMBQuery.py
NCMB/NCMBRequest.py
NCMB/NCMBSignature.py
NCMB/NCMBUser.py
NCMB/__init__.py
NCMB-1.3.1.dist-info/LICENSE
NCMB-1.3.1.dist-info/METADATA
NCMB-1.3.1.dist-info/WHEEL
NCMB-1.3.1.dist-info/top_level.txt
NCMB-1.3.1.dist-info/RECORD
