Metadata-Version: 2.1
Name: NCMB
Version: 1.3.1
Summary: NCMB is client SDK for Nifcloud mobile backend
Home-page: https://mbaas.nifcloud.com/
Author: goofmint
Author-email: atsushi@moongift.jp
Classifier: Programming Language :: Python :: 3.8
Classifier: License :: OSI Approved :: MIT License
Classifier: Operating System :: OS Independent
License-File: LICENSE
